{
  "date": "2026-03-27",
  "source": "yahoo_finance_flow_proxy",
  "note": "Flow proxy = \u00b1(volume \u00d7 price / 1M). Direction: + if close>open, \u2212 if close<open.",
  "btc": {
    "IBIT": -1668.3,
    "FBTC": -270.8,
    "BITB": -80.8,
    "ARKB": -140.9,
    "BTCO": -4.4,
    "EZBC": -4.0,
    "BRRR": -6.0,
    "HODL": -27.8,
    "BTCW": -1.0,
    "GBTC": -138.7,
    "BTC": -107.6
  },
  "eth": {
    "ETHA": -598.5,
    "FETH": -99.7,
    "ETHW": -16.1,
    "CETH": -16.8,
    "ETHV": -2.3,
    "QETH": -0.8,
    "EZET": -1.4,
    "ETHE": -39.9,
    "ETH": -79.8
  },
  "sol": {
    "GSOL": -7.0,
    "SOLZ": -8.5,
    "SOLT": -35.0
  },
  "scraped_at": "2026-03-27T04:08:03.875805+00:00"
}